hiphops_hook/__init__.py
hiphops_hook/client.py
hiphops_hook/exceptions.py
hiphops_hook/platform_utils.py
hiphops_hook/bin/hook-windows-amd64.exe
hiphops_hook/scripts/__init__.py
hiphops_hook/scripts/download.py
hiphops_hook/scripts/install.py
hiphops_hook/scripts/test.py
hiphops_hook-0.0.1a38.dist-info/METADATA
hiphops_hook-0.0.1a38.dist-info/WHEEL
hiphops_hook-0.0.1a38.dist-info/top_level.txt
hiphops_hook-0.0.1a38.dist-info/RECORD
