Metadata-Version: 2.4
Name: hiphops-hook
Version: 0.0.1a38
Summary: Python client for HipHops Hook
Author-email: "hiphops.io" <hello@hiphops.io>
License-Expression: MIT
Project-URL: Homepage, https://github.com/hiphops-io/hook
Project-URL: Repository, https://github.com/hiphops-io/hook.git
Project-URL: Issues, https://github.com/hiphops-io/hook/issues
Keywords: hiphops,hook,client
Classifier: Development Status :: 3 - Alpha
Classifier: Intended Audience :: Developers
Classifier: Programming Language :: Python :: 3
Classifier: Programming Language :: Python :: 3.8
Classifier: Programming Language :: Python :: 3.9
Classifier: Programming Language :: Python :: 3.10
Classifier: Programming Language :: Python :: 3.11
Classifier: Programming Language :: Python :: 3.12
Classifier: Operating System :: OS Independent
Classifier: Topic :: Software Development :: Libraries :: Python Modules
Requires-Python: >=3.8
Provides-Extra: dev
Requires-Dist: pytest>=6.0; extra == "dev"
Requires-Dist: pytest-cov>=2.0; extra == "dev"
Requires-Dist: black>=22.0; extra == "dev"
Requires-Dist: flake8>=4.0; extra == "dev"
Requires-Dist: mypy>=0.900; extra == "dev"
